alu.v
`timescale 1ns/10ps

module tb_alu();

	wire [15:0] out;
	wire z;
	reg [15:0] a,b;
	reg [2:0] op;
	reg clk;

	alu uut(out,z,a,b,op,clk);

	initial
		begin
		#00 clk = 1'b0;
		forever #10 clk = ~clk;
		end

	initial
		begin
		#20  op=3'd0; a=16'd54; b=16'd5;
		#20  op=3'd1; a=16'd54; b=16'd5;
		#20  op=3'd2; a=16'd54; b=16'd5;
		#20  op=3'd3; a=16'd54; b=16'd5;
		#20  op=3'd4; a=16'd54; b=16'd5;
		#20  op=3'd5; a=16'd54; b=16'd5;
		#20  op=3'd6; a=16'd54; b=16'd5;
		#20  op=3'd7; a=16'd54; b=16'd5;
		#20  $stop;
		end

	initial
		begin
		$dumpfile("alu.vcd");
		$dumpvars;
		end

endmodule

module alu (	out,z,
				a,b,
				alu_op,
				clk
				);

	output reg [15:0] out;
	output reg z;
	
	input wire [15:0] a,b;
	input wire [2:0] alu_op;
	input wire clk;

	parameter ADD 	= 3'b000 ;
	parameter SUB 	= 3'b001 ;
	parameter SHR 	= 3'b010 ;// shift right a by b bits
	parameter SHL 	= 3'b011 ;// shift left a by b bits 
	parameter NAND 	= 3'b100 ;
	parameter OR 	= 3'b101 ;
	parameter DIR 	= 3'b110 ;
	parameter SAR	= 3'b111 ;// shift arithmetic right

	always@(posedge clk)
	begin
		case(alu_op)
		ADD	:	begin	
					out <= a+b;
					z <= (out==0);
				end
		SUB	: 	begin
					out <= a-b;
					z <= (out==0);
				end
		SHR	:	begin
					out <= a>>b;
					z <= (out==0);
				end
		SHL	:	begin
					out <= a<<b;
					z <= (out==0);
				end
		NAND:	begin
					out <= ~(a&b);
					z <= (out==0);
				end
		OR	:	begin
					out <= a|b;
					z <= (out==0);
				end
		DIR	:	begin
					out <= a;
					z <= (out==0);
				end
		SAR	:	begin
					out <= {a[1],a[15:1]};
					z <= (out==0);
				end
		default:begin
					out <= 16'd0;
					z <= 1'bz;
				end
		endcase
	end

endmodule

alu.vcd
$date
	Sat Mar 31 22:17:46 2018
$end
$version
	Icarus Verilog
$end
$timescale
	10ps
$end
$scope module tb_alu $end
$var wire 1 ! z $end
$var wire 16 " out [15:0] $end
$var reg 16 # a [15:0] $end
$var reg 16 $ b [15:0] $end
$var reg 1 % clk $end
$var reg 3 & op [2:0] $end
$scope module uut $end
$var wire 16 ' a [15:0] $end
$var wire 3 ( alu_op [2:0] $end
$var wire 16 ) b [15:0] $end
$var wire 1 % clk $end
$var reg 16 * out [15:0] $end
$var reg 1 ! z $end
$upscope $end
$upscope $end
$enddefinitions $end
#0
$dumpvars
bx *
bx )
bx (
bx '
bx &
0%
bx $
bx #
bx "
x!
$end
#1000
z!
b0 "
b0 *
1%
#2000
0%
b101 $
b101 )
b110110 #
b110110 '
b0 &
b0 (
#3000
1!
b111011 "
b111011 *
1%
#4000
0%
b1 &
b1 (
#5000
0!
b110001 "
b110001 *
1%
#6000
0%
b10 &
b10 (
#7000
b1 "
b1 *
1%
#8000
0%
b11 &
b11 (
#9000
b11011000000 "
b11011000000 *
1%
#10000
0%
b100 &
b100 (
#11000
b1111111111111011 "
b1111111111111011 *
1%
#12000
0%
b101 &
b101 (
#13000
b110111 "
b110111 *
1%
#14000
0%
b110 &
b110 (
#15000
b110110 "
b110110 *
1%
#16000
0%
b111 &
b111 (
#17000
b1000000000011011 "
b1000000000011011 *
1%
