controllerFSM.v
`timescale 1ns/10ps 
module tb_controllerFSM();
reg [3:0] opcode, func_field;
reg clk, rst;

wire [5:0] NextState, CurrentState;

wire [1:0] PCSrc;
wire [2:0] ALUOp;
wire sign_extend;
wire ALUSrcA;
wire [2:0] ALUSrcB;
wire [1:0] ReadR1;
wire ReadR2;
wire RegWriteDst;
wire MemToReg;
wire PCBEqCond, PCBNqCond;
wire PCWrite;
wire MemWrite, MemRead;
wire IRWrite;
wire RegWrite;
wire WriteA, WriteB;

controllerFSM uut (.NextState(NextState), .CurrentState(CurrentState), .PCSrc(PCSrc), .ALUOp(ALUOp), .sign_extend(sign_extend), 
					.ALUSrcA(ALUSrcA) ,.ALUSrcB(ALUSrcB), .ReadR1(ReadR1), .ReadR2(ReadR2), 
					.RegWriteDst(RegWriteDst), .MemToReg(MemToReg), .PCBEqCond(PCBEqCond), 
					.PCBNqCond(PCBNqCond), .PCWrite(PCWrite), .MemWrite(MemWrite), 
					.MemRead(MemRead), .IRWrite(IRWrite), .RegWrite(RegWrite), 
					.WriteA(WriteA), .WriteB(WriteB), 
					.opcode(opcode),.func_field(func_field),.clk(clk),.rst(rst)
					);

initial
begin
	$dumpfile("controllerFSM.vcd");
	$dumpvars;
end

initial
begin
	#0000 clk <= 1'b0;
	forever #5 clk <= ~clk;
end

initial
begin
	#0000 rst = 1'b1;
	#0005 rst = 1'b0;
end

initial
begin
	#0010 opcode <= 1000;
	#0100 $stop;
end

initial
begin
//$monitor("time=%4d, PCSrc=%2b, ALUOp=%3b, sign_extend=%1b,ALUSrcA=%1b ,ALUSrcB=%3b, ReadR1=%2b, ReadR2=%1b, RegWriteDst=%1b, MemToReg=%1b, PCBEqCond=%1b, PCBNqCond=%1b, PCWrite=%1b, MemWrite=%1b, MemRead=%1b, IRWrite=%1b, RegWrite=%1b, WriteA=%1b, WriteB=%1b, opcode=%4b,func_field=%4b, clk=%1b, rst=%1b",$time, PCSrc, ALUOp, sign_extend, ALUSrcA ,ALUSrcB, ReadR1, ReadR2, RegWriteDst, MemToReg, PCBEqCond, PCBNqCond, PCWrite, MemWrite, MemRead, IRWrite, RegWrite, WriteA, WriteB, opcode,func_field, clk, rst);
$monitor("time=%4d, NextState=%6b, CurrentState=%6b, opcode=%4b, func_field=%4b, clk=%b, rst=%b", $time, NextState, CurrentState, opcode, func_field, clk, rst);
end

endmodule

module controllerFSM(NextState, CurrentState, PCSrc, ALUOp, sign_extend, 
					ALUSrcA ,ALUSrcB, ReadR1, ReadR2, 
					RegWriteDst, MemToReg, PCBEqCond, 
					PCBNqCond, PCWrite, MemWrite, 
					MemRead, IRWrite, RegWrite, 
					WriteA, WriteB, 
					opcode,func_field, clk, rst);

output reg [5:0] NextState, CurrentState;

output reg [1:0] PCSrc;
output reg [2:0] ALUOp;
output reg sign_extend;
output reg ALUSrcA;
output reg [2:0] ALUSrcB;
output reg [1:0] ReadR1;
output reg ReadR2;
output reg RegWriteDst;
output reg MemToReg;
output reg PCBEqCond, PCBNqCond;
output reg PCWrite;
output reg MemWrite, MemRead;
output reg IRWrite;
output reg RegWrite;
output reg WriteA, WriteB;

input wire [3:0] opcode, func_field;
input wire clk, rst;

parameter I_FETCH = 6'b00_0000;
parameter I_DECODE = 6'b00_0001;

parameter EX_ADD = 6'b00_0010;
parameter EX_ADDI1 = 6'b00_0011;
parameter EX_ADDI2 = 6'b00_0100;
parameter EX_LW_SW = 6'b00_0101;
parameter EX_BEQ = 6'b00_0110;
parameter EX_BNQ = 6'b00_0111;
parameter EX_JMP = 6'b00_1000;
parameter EX_NAND = 6'b00_1001;
parameter EX_NANDI = 6'b00_1010;
parameter EX_OR = 6'b00_1110;
parameter EX_ORI = 6'b00_1111;
parameter EX_SUB = 6'b01_0000;
parameter EX_SUBI1 = 6'b01_0001;
parameter EX_SUBI2 = 6'b01_0010;
parameter EX_SLL = 6'b10_0100;
parameter EX_SRL = 6'b10_0101;
parameter EX_SRA = 6'b10_0110;


parameter MEM_SW = 6'b01_0110;
parameter MEM_LW = 6'b10_0011;
parameter MEM_RTYPE = 6'b10_1000;
parameter WRITEBACK = 6'b11_1111;

parameter OP_ADD = 4'b1000;
parameter OP_ADDI1 = 4'b1001;
parameter OP_ADDI2 = 4'b1010;
parameter OP_SUB = 4'b1100;
parameter OP_SUBI1 = 4'b1101;
parameter OP_SUBI2 = 4'b1110;
parameter OP_SHIFT = 4'b0000;
parameter FF_SHIFT_LEFT_LOGICAL = 4'b0001;
parameter FF_SHIFT_RIGHT_LOGICAL = 4'b0010;
parameter FF_SHIFT_RIGHT_ARITHMETIC = 4'b0011;
parameter OP_NAND = 4'b1011;
parameter OP_NANDI = 4'b0111;
parameter OP_OR = 4'b1111;
parameter OP_ORI = 4'b0110;
parameter OP_BEQ = 4'b0100;
parameter OP_BNQ = 4'b0101;
parameter OP_JMP = 4'b0011;
parameter OP_LW = 4'b0001;
parameter OP_SW = 4'b0010;

// To update the state
always @(posedge clk or rst) 
begin
	if (rst) begin
				CurrentState <= I_FETCH;
				NextState <= I_FETCH;
			end
	else 	 CurrentState <= NextState;
end

// To calculate the next state
always@(*)
begin
case(CurrentState)
I_FETCH		:NextState <= I_DECODE;
I_DECODE	:begin
				case(opcode)
				OP_ADD 		:	NextState <= EX_ADD;
				OP_ADDI1	:	NextState <= EX_ADDI1;
				OP_ADDI2  	: 	NextState <= EX_ADDI2;
				OP_SUB 		:	NextState <= EX_SUB;
				OP_SUBI1	:	NextState <= EX_SUBI1;
				OP_SUBI2	:	NextState <= EX_SUBI2;
				OP_SHIFT	:	begin
									if (func_field == FF_SHIFT_LEFT_LOGICAL) begin
										NextState <= EX_SLL;
									end
									else if(func_field == FF_SHIFT_RIGHT_LOGICAL) begin
										NextState <= EX_SRL;
									end
									else if (func_field == FF_SHIFT_RIGHT_ARITHMETIC) begin
										NextState <= EX_SRA;
									end
									else begin
										NextState <= I_FETCH;
									end
								end
				OP_NAND 	:	NextState <= EX_NAND;
				OP_NANDI	:	NextState <= EX_NANDI;
				OP_OR 		:	NextState <= EX_OR;
				OP_ORI 		: 	NextState <= EX_ORI;
				OP_BEQ		:	NextState <= EX_BEQ;
				OP_BNQ		:	NextState <= EX_BNQ;
				OP_JMP		: 	NextState <= EX_JMP;
				OP_LW		: 	NextState <= EX_LW_SW;
				OP_SW		:	NextState <= EX_LW_SW;
				default		: 	NextState <= I_FETCH;
				endcase
			end
EX_ADD 		:NextState <= MEM_RTYPE;
EX_ADDI1	:NextState <= MEM_RTYPE;
EX_ADDI2 	:NextState <= MEM_RTYPE;
EX_SUB 		:NextState <= MEM_RTYPE;
EX_SUBI1 	:NextState <= MEM_RTYPE;
EX_SUBI2	:NextState <= MEM_RTYPE;
EX_SLL		:NextState <= MEM_RTYPE;
EX_SRL		:NextState <= MEM_RTYPE;
EX_SRA		:NextState <= MEM_RTYPE;
EX_NAND 	:NextState <= MEM_RTYPE;
EX_NANDI 	:NextState <= MEM_RTYPE;
EX_OR 		:NextState <= MEM_RTYPE;
EX_ORI		:NextState <= MEM_RTYPE;
EX_BEQ 		:NextState <= I_FETCH;
EX_BNQ		:NextState <= I_FETCH;
EX_JMP		:NextState <= I_FETCH;
EX_LW_SW	:begin
				if (opcode == OP_LW) NextState <= MEM_LW;
				else if (opcode == OP_SW) NextState <= MEM_SW;
				else NextState <= I_FETCH;
			 end
MEM_RTYPE 	:NextState <= I_FETCH;
MEM_SW 		:NextState <= I_FETCH;
MEM_LW 		:NextState <= WRITEBACK;
WRITEBACK	:NextState <= I_FETCH;
default		:NextState <= I_FETCH;
endcase
end
// Output Calculation in MOORE it is only state dependent
always@(*)
begin
case(CurrentState)
I_FETCH		:begin
				PCSrc		<= 2'b00;
				ALUOp		<= 3'b000;
				sign_extend	<= 1'bx;
				ALUSrcA		<= 1'b0;
				ALUSrcB		<= 3'b001;
				ReadR1		<= 2'bxx;
				ReadR2		<= 1'bx;
				RegWriteDst	<= 1'bx;
				MemToReg	<= 1'bx;
				PCBEqCond	<= 1'b0;
				PCBNqCond	<= 1'b0;
				PCWrite		<= 1'b1;
				MemWrite	<= 1'b0;
				MemRead		<= 1'b0;
				IRWrite		<= 1'b0;
				RegWrite 	<= 1'b0;
				WriteA 		<= 1'b0;
				WriteB 		<= 1'b0;
			end
I_DECODE	:begin
				PCSrc		<= 2'bxx;
				ALUOp		<= 3'bxxx;
				sign_extend	<= 1'bx;
				ALUSrcA		<= 1'b0;
				ALUSrcB		<= 3'b001;
				ReadR1		<= 2'b00;
				ReadR2		<= 1'b0;
				RegWriteDst	<= 1'bx;
				MemToReg	<= 1'bx;
				PCBEqCond	<= 1'b0;
				PCBNqCond	<= 1'b0;
				PCWrite		<= 1'b0;
				MemWrite	<= 1'b0;
				MemRead		<= 1'b0;
				IRWrite		<= 1'b0;
				RegWrite 	<= 1'b0;
				WriteA 		<= 1'b1;
				WriteB 		<= 1'b1;
			end
EX_ADD 		:begin
				PCSrc		<= 2'bxx;
				ALUOp		<= 3'b000;
				sign_extend	<= 1'bx;
				ALUSrcA		<= 1'b1;
				ALUSrcB		<= 3'b010;
				ReadR1		<= 2'b00;
				ReadR2		<= 1'b0;
				RegWriteDst	<= 1'b1;
				MemToReg	<= 1'bx;
				PCBEqCond	<= 1'b0;
				PCBNqCond	<= 1'b0;
				PCWrite		<= 1'b0;
				MemWrite	<= 1'b0;
				MemRead		<= 1'b0;
				IRWrite		<= 1'b0;
				RegWrite 	<= 1'b0;
				WriteA 		<= 1'b1;
				WriteB 		<= 1'b1;
			end
EX_ADDI1	:begin
				PCSrc		<= 2'bxx;
				ALUOp		<= 3'b000;
				sign_extend	<= 1'b1;
				ALUSrcA		<= 1'b1;
				ALUSrcB		<= 3'b010;
				ReadR1		<= 2'b01;
				ReadR2		<= 1'b0;
				RegWriteDst	<= 1'b1;
				MemToReg	<= 1'bx;
				PCBEqCond	<= 1'b0;
				PCBNqCond	<= 1'b0;
				PCWrite		<= 1'b0;
				MemWrite	<= 1'b0;
				MemRead		<= 1'b0;
				IRWrite		<= 1'b0;
				RegWrite 	<= 1'b0;
				WriteA 		<= 1'b1;
				WriteB 		<= 1'b1;
			end
EX_ADDI2	:begin
				PCSrc		<= 2'bxx;
				ALUOp		<= 3'b000;
				sign_extend	<= 1'b0;
				ALUSrcA		<= 1'b1;
				ALUSrcB		<= 3'b010;
				ReadR1		<= 2'b01;
				ReadR2		<= 1'b0;
				RegWriteDst	<= 1'b1;
				MemToReg	<= 1'bx;
				PCBEqCond	<= 1'b0;
				PCBNqCond	<= 1'b0;
				PCWrite		<= 1'b0;
				MemWrite	<= 1'b0;
				MemRead		<= 1'b0;
				IRWrite		<= 1'b0;
				RegWrite 	<= 1'b0;
				WriteA 		<= 1'b1;
				WriteB 		<= 1'b1;
			end
EX_SUB 		:begin
				PCSrc		<= 2'bxx;
				ALUOp		<= 3'b001;
				sign_extend	<= 1'bx;
				ALUSrcA		<= 1'b1;
				ALUSrcB		<= 3'b000;
				ReadR1		<= 2'b00;
				ReadR2		<= 1'b0;
				RegWriteDst	<= 1'b1;
				MemToReg	<= 1'bx;
				PCBEqCond	<= 1'b0;
				PCBNqCond	<= 1'b0;
				PCWrite		<= 1'b0;
				MemWrite	<= 1'b0;
				MemRead		<= 1'b0;
				IRWrite		<= 1'b0;
				RegWrite 	<= 1'b0;
				WriteA 		<= 1'b1;
				WriteB 		<= 1'b1;
			end
EX_SUBI1	:begin
				PCSrc		<= 2'bxx;
				ALUOp		<= 3'b001;
				sign_extend	<= 1'b1;
				ALUSrcA		<= 1'b1;
				ALUSrcB		<= 3'b010;
				ReadR1		<= 2'b01;
				ReadR2		<= 1'b0;
				RegWriteDst	<= 1'b1;
				MemToReg	<= 1'bx;
				PCBEqCond	<= 1'b0;
				PCBNqCond	<= 1'b0;
				PCWrite		<= 1'b0;
				MemWrite	<= 1'b0;
				MemRead		<= 1'b0;
				IRWrite		<= 1'b0;
				RegWrite 	<= 1'b0;
				WriteA 		<= 1'b1;
				WriteB 		<= 1'b1;
			end
EX_SUBI2	:begin
				PCSrc		<= 2'bxx;
				ALUOp		<= 3'b001;
				sign_extend	<= 1'b0;
				ALUSrcA		<= 1'b1;
				ALUSrcB		<= 3'b010;
				ReadR1		<= 2'b01;
				ReadR2		<= 1'b0;
				RegWriteDst	<= 1'b1;
				MemToReg	<= 1'bx;
				PCBEqCond	<= 1'b0;
				PCBNqCond	<= 1'b0;
				PCWrite		<= 1'b0;
				MemWrite	<= 1'b0;
				MemRead		<= 1'b0;
				IRWrite		<= 1'b0;
				RegWrite 	<= 1'b0;
				WriteA 		<= 1'b1;
				WriteB 		<= 1'b1;
			end
EX_SLL		:begin // NOT MADE YET
				PCSrc		<= 2'bxx;
				ALUOp		<= 3'b001;
				sign_extend	<= 1'b0;
				ALUSrcA		<= 1'b1;
				ALUSrcB		<= 3'b010;
				ReadR1		<= 2'b01;
				ReadR2		<= 1'b0;
				RegWriteDst	<= 1'b1;
				MemToReg	<= 1'bx;
				PCBEqCond	<= 1'b0;
				PCBNqCond	<= 1'b0;
				PCWrite		<= 1'b0;
				MemWrite	<= 1'b0;
				MemRead		<= 1'b0;
				IRWrite		<= 1'b0;
				RegWrite 	<= 1'b0;
				WriteA 		<= 1'b1;
				WriteB 		<= 1'b1;
			end
EX_SRL		:begin // NOT MADE YET
				PCSrc		<= 2'bxx;
				ALUOp		<= 3'b001;
				sign_extend	<= 1'b0;
				ALUSrcA		<= 1'b1;
				ALUSrcB		<= 3'b010;
				ReadR1		<= 2'b01;
				ReadR2		<= 1'b0;
				RegWriteDst	<= 1'b1;
				MemToReg	<= 1'bx;
				PCBEqCond	<= 1'b0;
				PCBNqCond	<= 1'b0;
				PCWrite		<= 1'b0;
				MemWrite	<= 1'b0;
				MemRead		<= 1'b0;
				IRWrite		<= 1'b0;
				RegWrite 	<= 1'b0;
				WriteA 		<= 1'b1;
				WriteB 		<= 1'b1;
			end
EX_SRA		:begin // NOT MADE YET
				PCSrc		<= 2'bxx;
				ALUOp		<= 3'b001;
				sign_extend	<= 1'b0;
				ALUSrcA		<= 1'b1;
				ALUSrcB		<= 3'b010;
				ReadR1		<= 2'b01;
				ReadR2		<= 1'b0;
				RegWriteDst	<= 1'b1;
				MemToReg	<= 1'bx;
				PCBEqCond	<= 1'b0;
				PCBNqCond	<= 1'b0;
				PCWrite		<= 1'b0;
				MemWrite	<= 1'b0;
				MemRead		<= 1'b0;
				IRWrite		<= 1'b0;
				RegWrite 	<= 1'b0;
				WriteA 		<= 1'b1;
				WriteB 		<= 1'b1;
			end
EX_NAND		:begin
				PCSrc		<= 2'bxx;
				ALUOp		<= 3'b010;
				sign_extend	<= 1'bx;
				ALUSrcA		<= 1'b1;
				ALUSrcB		<= 3'b000;
				ReadR1		<= 2'b00;
				ReadR2		<= 1'b0;
				RegWriteDst	<= 1'b1;
				MemToReg	<= 1'bx;
				PCBEqCond	<= 1'b0;
				PCBNqCond	<= 1'b0;
				PCWrite		<= 1'b0;
				MemWrite	<= 1'b0;
				MemRead		<= 1'b0;
				IRWrite		<= 1'b0;
				RegWrite 	<= 1'b0;
				WriteA 		<= 1'b1;
				WriteB 		<= 1'b1;
			end
EX_NANDI	:begin
				PCSrc		<= 2'bxx;
				ALUOp		<= 3'b010;
				sign_extend	<= 1'bx;
				ALUSrcA		<= 1'b1;
				ALUSrcB		<= 3'b010;
				ReadR1		<= 2'b01;
				ReadR2		<= 1'bx;
				RegWriteDst	<= 1'b1;
				MemToReg	<= 1'bx;
				PCBEqCond	<= 1'b0;
				PCBNqCond	<= 1'b0;
				PCWrite		<= 1'b0;
				MemWrite	<= 1'b0;
				MemRead		<= 1'b0;
				IRWrite		<= 1'b0;
				RegWrite 	<= 1'b0;
				WriteA 		<= 1'b1;
				WriteB 		<= 1'b1;
			end
EX_OR		:begin
				PCSrc		<= 2'bxx;
				ALUOp		<= 3'b101;
				sign_extend	<= 1'bx;
				ALUSrcA		<= 1'b1;
				ALUSrcB		<= 3'b000;
				ReadR1		<= 2'b00;
				ReadR2		<= 1'b0;
				RegWriteDst	<= 1'b1;
				MemToReg	<= 1'bx;
				PCBEqCond	<= 1'b0;
				PCBNqCond	<= 1'b0;
				PCWrite		<= 1'b0;
				MemWrite	<= 1'b0;
				MemRead		<= 1'b0;
				IRWrite		<= 1'b0;
				RegWrite 	<= 1'b0;
				WriteA 		<= 1'b1;
				WriteB 		<= 1'b1;
			end
EX_ORI		:begin
				PCSrc		<= 2'bxx;
				ALUOp		<= 3'b101;
				sign_extend	<= 1'b1;
				ALUSrcA		<= 1'b1;
				ALUSrcB		<= 3'b010;
				ReadR1		<= 2'b01;
				ReadR2		<= 1'b0;
				RegWriteDst	<= 1'b1;
				MemToReg	<= 1'bx;
				PCBEqCond	<= 1'b0;
				PCBNqCond	<= 1'b0;
				PCWrite		<= 1'b0;
				MemWrite	<= 1'b0;
				MemRead		<= 1'b0;
				IRWrite		<= 1'b0;
				RegWrite 	<= 1'b0;
				WriteA 		<= 1'b1;
				WriteB 		<= 1'b1;
			end
EX_BEQ		:begin
				PCSrc		<= 2'b00;
				ALUOp		<= 3'b001;
				sign_extend	<= 1'bx;
				ALUSrcA		<= 1'b1;
				ALUSrcB		<= 3'b000;
				ReadR1		<= 2'b01;
				ReadR2		<= 1'bx;
				RegWriteDst	<= 1'bx;
				MemToReg	<= 1'bx;
				PCBEqCond	<= 1'b1;
				PCBNqCond	<= 1'b0;
				PCWrite		<= 1'b0;
				MemWrite	<= 1'b0;
				MemRead		<= 1'b0;
				IRWrite		<= 1'b0;
				RegWrite 	<= 1'b0;
				WriteA 		<= 1'b0;
				WriteB 		<= 1'b0;
			end
EX_BNQ		:begin
				PCSrc		<= 2'b00;
				ALUOp		<= 3'b001;
				sign_extend	<= 1'bx;
				ALUSrcA		<= 1'b1;
				ALUSrcB		<= 3'b000;
				ReadR1		<= 2'b01;
				ReadR2		<= 1'bx;
				RegWriteDst	<= 1'bx;
				MemToReg	<= 1'bx;
				PCBEqCond	<= 1'b0;
				PCBNqCond	<= 1'b1;
				PCWrite		<= 1'b0;
				MemWrite	<= 1'b0;
				MemRead		<= 1'b0;
				IRWrite		<= 1'b0;
				RegWrite 	<= 1'b0;
				WriteA 		<= 1'b0;
				WriteB 		<= 1'b0;
			end
EX_JMP		:begin
				PCSrc		<= 2'b01;
				ALUOp		<= 3'b000;
				sign_extend	<= 1'bx;
				ALUSrcA		<= 1'b0;
				ALUSrcB		<= 3'b100;
				ReadR1		<= 2'bxx;
				ReadR2		<= 1'bx;
				RegWriteDst	<= 1'bx;
				MemToReg	<= 1'bx;
				PCBEqCond	<= 1'b0;
				PCBNqCond	<= 1'b0;
				PCWrite		<= 1'b1;
				MemWrite	<= 1'b0;
				MemRead		<= 1'b0;
				IRWrite		<= 1'b0;
				RegWrite 	<= 1'b0;
				WriteA 		<= 1'b0;
				WriteB 		<= 1'b0;
			end
EX_LW_SW	:begin
				PCSrc		<= 2'bxx;
				ALUOp		<= 3'b000;
				sign_extend	<= 1'b1;
				ALUSrcA		<= 1'b1;
				ALUSrcB		<= 3'b011;
				ReadR1		<= 2'b10;
				ReadR2		<= 1'b1;
				RegWriteDst	<= 1'b0;
				MemToReg	<= 1'bx;
				PCBEqCond	<= 1'b0;
				PCBNqCond	<= 1'b0;
				PCWrite		<= 1'b0;
				MemWrite	<= 1'b0;
				MemRead		<= 1'b0;
				IRWrite		<= 1'b0;
				RegWrite 	<= 1'b0;
				WriteA 		<= 1'b1;
				WriteB 		<= 1'b1;
			end
MEM_RTYPE	:begin
				PCSrc		<= 2'bxx;
				ALUOp		<= 3'bxxx;
				sign_extend	<= 1'bx;
				ALUSrcA		<= 1'bx;
				ALUSrcB		<= 3'bxxx;
				ReadR1		<= 2'bxx;
				ReadR2		<= 1'bx;
				RegWriteDst	<= 1'bx;
				MemToReg	<= 1'bx;
				PCBEqCond	<= 1'bx;
				PCBNqCond	<= 1'bx;
				PCWrite		<= 1'b0;
				MemWrite	<= 1'b0;
				MemRead		<= 1'b0;
				IRWrite		<= 1'b0;
				RegWrite 	<= 1'b0;
				WriteA 		<= 1'b0;
				WriteB 		<= 1'b0;
			end
MEM_LW		:begin
				PCSrc		<= 2'bxx;
				ALUOp		<= 3'bxxx;
				sign_extend	<= 1'bx;
				ALUSrcA		<= 1'bx;
				ALUSrcB		<= 3'bxxx;
				ReadR1		<= 2'bxx;
				ReadR2		<= 1'bx;
				RegWriteDst	<= 1'bx;
				MemToReg	<= 1'bx;
				PCBEqCond	<= 1'bx;
				PCBNqCond	<= 1'bx;
				PCWrite		<= 1'b0;
				MemWrite	<= 1'b0;
				MemRead		<= 1'b1;
				IRWrite		<= 1'b0;
				RegWrite 	<= 1'b0;
				WriteA 		<= 1'b0;
				WriteB 		<= 1'b0;
			end
MEM_SW		:begin
				PCSrc		<= 2'bxx;
				ALUOp		<= 3'bxxx;
				sign_extend	<= 1'bx;
				ALUSrcA		<= 1'bx;
				ALUSrcB		<= 3'bxxx;
				ReadR1		<= 2'bxx;
				ReadR2		<= 1'b1;
				RegWriteDst	<= 1'bx;
				MemToReg	<= 1'bx;
				PCBEqCond	<= 1'bx;
				PCBNqCond	<= 1'bx;
				PCWrite		<= 1'b0;
				MemWrite	<= 1'b1;
				MemRead		<= 1'b0;
				IRWrite		<= 1'b0;
				RegWrite 	<= 1'b0;
				WriteA 		<= 1'b0;
				WriteB 		<= 1'b0;
			end
WRITEBACK	:begin
				PCSrc		<= 2'bxx;
				ALUOp		<= 3'bxxx;
				sign_extend	<= 1'bx;
				ALUSrcA		<= 1'bx;
				ALUSrcB		<= 3'bxxx;
				ReadR1		<= 2'bxx;
				ReadR2		<= 1'bx;
				RegWriteDst	<= 1'b1;
				MemToReg	<= 1'bx;
				PCBEqCond	<= 1'bx;
				PCBNqCond	<= 1'bx;
				PCWrite		<= 1'b0;
				MemWrite	<= 1'b0;
				MemRead		<= 1'b0;
				IRWrite		<= 1'b0;
				RegWrite 	<= 1'b1;
				WriteA 		<= 1'b0;
				WriteB 		<= 1'b0;
			end
endcase
end

endmodule

controllerFSM.vcd
$date
	Tue Mar 27 04:45:36 2018
$end
$version
	Icarus Verilog
$end
$timescale
	10ps
$end
$scope module tb_controllerFSM $end
$var wire 3 ! ALUOp [2:0] $end
$var wire 1 " ALUSrcA $end
$var wire 3 # ALUSrcB [2:0] $end
$var wire 6 $ CurrentState [5:0] $end
$var wire 1 % IRWrite $end
$var wire 1 & MemRead $end
$var wire 1 ' MemToReg $end
$var wire 1 ( MemWrite $end
$var wire 6 ) NextState [5:0] $end
$var wire 1 * PCBEqCond $end
$var wire 1 + PCBNqCond $end
$var wire 2 , PCSrc [1:0] $end
$var wire 1 - PCWrite $end
$var wire 2 . ReadR1 [1:0] $end
$var wire 1 / ReadR2 $end
$var wire 1 0 RegWrite $end
$var wire 1 1 RegWriteDst $end
$var wire 1 2 WriteA $end
$var wire 1 3 WriteB $end
$var wire 1 4 sign_extend $end
$var reg 1 5 clk $end
$var reg 4 6 func_field [3:0] $end
$var reg 4 7 opcode [3:0] $end
$var reg 1 8 rst $end
$scope module uut $end
$var wire 1 9 clk $end
$var wire 4 : func_field [3:0] $end
$var wire 4 ; opcode [3:0] $end
$var wire 1 < rst $end
$var reg 3 = ALUOp [2:0] $end
$var reg 1 > ALUSrcA $end
$var reg 3 ? ALUSrcB [2:0] $end
$var reg 6 @ CurrentState [5:0] $end
$var reg 1 A IRWrite $end
$var reg 1 B MemRead $end
$var reg 1 C MemToReg $end
$var reg 1 D MemWrite $end
$var reg 6 E NextState [5:0] $end
$var reg 1 F PCBEqCond $end
$var reg 1 G PCBNqCond $end
$var reg 2 H PCSrc [1:0] $end
$var reg 1 I PCWrite $end
$var reg 2 J ReadR1 [1:0] $end
$var reg 1 K ReadR2 $end
$var reg 1 L RegWrite $end
$var reg 1 M RegWriteDst $end
$var reg 1 N WriteA $end
$var reg 1 O WriteB $end
$var reg 1 P sign_extend $end
$upscope $end
$upscope $end
$enddefinitions $end
#0
$dumpvars
xP
0O
0N
xM
0L
xK
bx J
1I
b0 H
0G
0F
b1 E
0D
xC
0B
0A
b0 @
b1 ?
0>
b0 =
1<
bx ;
bx :
09
18
bx 7
bx 6
05
x4
03
02
x1
00
x/
bx .
1-
b0 ,
0+
0*
b1 )
0(
x'
0&
0%
b0 $
b1 #
0"
b0 !
$end
#500
1O
13
1N
12
0I
0-
0K
0/
b0 J
b0 .
bx =
bx !
bx H
bx ,
b0 E
b0 )
b1 @
b1 $
15
19
08
0<
#1000
b10 E
b10 )
05
09
b1000 7
b1000 ;
#1500
1M
11
b10 ?
b10 #
1>
1"
b0 =
b0 !
b101000 E
b101000 )
b10 @
b10 $
15
19
#2000
05
09
#2500
0O
03
0N
02
xG
x+
xF
x*
xM
x1
xK
x/
bx J
bx .
bx ?
bx #
x>
x"
bx =
bx !
b0 E
b0 )
b101000 @
b101000 $
15
19
#3000
05
09
#3500
1I
1-
0G
0+
0F
0*
b1 ?
b1 #
0>
0"
b0 =
b0 !
b0 H
b0 ,
b1 E
b1 )
b0 @
b0 $
15
19
#4000
05
09
#4500
1O
13
1N
12
0I
0-
0K
0/
b0 J
b0 .
bx =
bx !
bx H
bx ,
b10 E
b10 )
b1 @
b1 $
15
19
#5000
05
09
#5500
1M
11
b10 ?
b10 #
1>
1"
b0 =
b0 !
b101000 E
b101000 )
b10 @
b10 $
15
19
#6000
05
09
#6500
0O
03
0N
02
xG
x+
xF
x*
xM
x1
xK
x/
bx J
bx .
bx ?
bx #
x>
x"
bx =
bx !
b0 E
b0 )
b101000 @
b101000 $
15
19
#7000
05
09
#7500
1I
1-
0G
0+
0F
0*
b1 ?
b1 #
0>
0"
b0 =
b0 !
b0 H
b0 ,
b1 E
b1 )
b0 @
b0 $
15
19
#8000
05
09
#8500
1O
13
1N
12
0I
0-
0K
0/
b0 J
b0 .
bx =
bx !
bx H
bx ,
b10 E
b10 )
b1 @
b1 $
15
19
#9000
05
09
#9500
1M
11
b10 ?
b10 #
1>
1"
b0 =
b0 !
b101000 E
b101000 )
b10 @
b10 $
15
19
#10000
05
09
#10500
0O
03
0N
02
xG
x+
xF
x*
xM
x1
xK
x/
bx J
bx .
bx ?
bx #
x>
x"
bx =
bx !
b0 E
b0 )
b101000 @
b101000 $
15
19
