dataMemory.v
`timescale 1ns/10ps
module tb_dataMemory();

reg [15:0] A_DataAddress;
reg [15:0] D_WriteData;
reg C_DMRead, C_DMWrite, clk, rst;
wire [15:0] D_Data;

dataMemory uut (D_Data,	A_DataAddress,D_WriteData,C_DMRead, C_DMWrite,clk, rst);

initial
begin
	#00 clk <= 1'b0;
	forever #10 clk <= ~clk;
end

initial
begin
	#00 rst = 1'b1;
	#30 rst = 1'b0;
end

initial
begin
	#00  C_DMRead = 1'b1; C_DMWrite = 1'b0;
	#200 C_DMRead = 1'b0; C_DMWrite = 1'b1;
	#200 C_DMRead = 1'b0; C_DMWrite = 1'b0;
	#200 C_DMRead = 1'b1; C_DMWrite = 1'b1; 
	#200 $stop;
end

initial
begin
	#00 A_DataAddress <= 16'd0;
	#50 A_DataAddress <= 16'd1;
	#50 A_DataAddress <= 16'd1;
	#50 A_DataAddress <= 16'd2;
end

initial
begin
	#00  D_WriteData = 16'd20;
end

initial
begin
	$dumpfile("dataMemory.vcd");
	$dumpvars;
end

initial
begin
	$monitor("time=%3d, D_Data=%16h, D_WriteData=%16h, A_DataAddress=%16h", $time, D_Data, D_WriteData, A_DataAddress);
end

endmodule


module dataMemory(	D_Data,
					A_DataAddress,
					D_WriteData,
					C_DMRead, C_DMWrite,
					clk, rst
					);

output reg [15:0] D_Data;
input wire [15:0] A_DataAddress;
input wire [15:0] D_WriteData;
input wire C_DMRead, C_DMWrite;
input wire clk, rst;

reg [15:0] memory[0:8192]; // 8192 = 8*1024, 8k*2bytes=16kB
initial $readmemh("data_file.txt", memory);

always @(posedge clk or rst) begin
	if (rst == 1) begin
		D_Data = 16'b0000_0000_0000_0000;
	end
	else begin
		if (C_DMWrite == 1) begin
			memory[A_DataAddress] <= D_WriteData;
		end
		else begin
			memory[A_DataAddress] <= memory[A_DataAddress];
		end

		if (C_DMRead == 1) begin
			D_Data <= memory[A_DataAddress];
		end
		else begin
			D_Data <= D_Data;
		end
	end 
end

endmodule

dataMemory.vcd
$date
	Sun Apr  1 18:38:17 2018
$end
$version
	Icarus Verilog
$end
$timescale
	10ps
$end
$scope module tb_dataMemory $end
$var wire 16 ! D_Data [15:0] $end
$var reg 16 " A_DataAddress [15:0] $end
$var reg 1 # C_DMRead $end
$var reg 1 $ C_DMWrite $end
$var reg 16 % D_WriteData [15:0] $end
$var reg 1 & clk $end
$var reg 1 ' rst $end
$scope module uut $end
$var wire 16 ( A_DataAddress [15:0] $end
$var wire 1 ) C_DMRead $end
$var wire 1 * C_DMWrite $end
$var wire 16 + D_WriteData [15:0] $end
$var wire 1 , clk $end
$var wire 1 - rst $end
$var reg 16 . D_Data [15:0] $end
$upscope $end
$upscope $end
$enddefinitions $end
#0
$dumpvars
b0 .
1-
0,
b10100 +
0*
1)
b0 (
1'
0&
b10100 %
0$
1#
b0 "
b0 !
$end
#1000
1&
1,
#2000
0&
0,
#3000
b100010101100001 .
b100010101100001 !
1&
1,
0'
0-
#4000
0&
0,
#5000
b100010101100111 .
b100010101100111 !
1&
1,
b1 "
b1 (
#6000
0&
0,
#7000
1&
1,
#8000
0&
0,
#9000
1&
1,
#10000
0&
0,
#11000
1&
1,
#12000
0&
0,
#13000
1&
1,
#14000
0&
0,
#15000
b1000000010000 .
b1000000010000 !
1&
1,
b10 "
b10 (
#16000
0&
0,
#17000
1&
1,
#18000
0&
0,
#19000
1&
1,
#20000
0&
0,
1$
1*
0#
0)
#21000
1&
1,
#22000
0&
0,
#23000
1&
1,
#24000
0&
0,
#25000
1&
1,
#26000
0&
0,
#27000
1&
1,
#28000
0&
0,
#29000
1&
1,
#30000
0&
0,
#31000
1&
1,
#32000
0&
0,
#33000
1&
1,
#34000
0&
0,
#35000
1&
1,
#36000
0&
0,
#37000
1&
1,
#38000
0&
0,
#39000
1&
1,
#40000
0&
0,
0$
0*
#41000
1&
1,
#42000
0&
0,
#43000
1&
1,
#44000
0&
0,
#45000
1&
1,
#46000
0&
0,
#47000
1&
1,
#48000
0&
0,
#49000
1&
1,
#50000
0&
0,
#51000
1&
1,
#52000
0&
0,
#53000
1&
1,
#54000
0&
0,
#55000
1&
1,
#56000
0&
0,
#57000
1&
1,
#58000
0&
0,
#59000
1&
1,
#60000
0&
0,
1$
1*
1#
1)
#61000
b10100 .
b10100 !
1&
1,
