registerFile.v
module registerFile(	D_ReadReg1RT, D_ReadReg2RT,
						D_Offset, D_RegSW,
						D_BT,
						D_MDR_IN, D_ALU_IN,	
						A_ReadReg1RT, A_ReadReg2RT,
						A_Offset, A_RegSWLW,
						A_WriteRegRT_BT,
						C_RegDstWrite, C_RegWrite, C_MemToReg,
						clk, rst
						);


output reg [15:0] D_ReadReg1RT, D_ReadReg2RT;
output reg [15:0] D_Offset, D_RegSW;
output reg [15:0] D_BT;

input wire [3:0] A_ReadReg1RT, A_ReadReg2RT;
input wire [3:0] A_Offset, A_RegSWLW;
input wire [3:0] A_WriteRegRT_BT;
input wire [15:0] D_MDR_IN, D_ALU_IN;

input wire C_RegDstWrite, C_RegWrite, C_MemToReg;
input wire clk, rst;

reg [15:0] memory[0:15];
reg [3:0] a_write;
reg [15:0] d_write;

initial 
$readmemh("rf_data.txt",memory);
always@(*)
begin
		// Selecting Address to write to RF
		if (C_RegDstWrite == 1)
		begin
		a_write = A_WriteRegRT_BT;
		end
		else begin
			a_write = A_RegSWLW;
		end
		// Selecting Data to write to RF
		if (C_MemToReg == 1)
		begin
			d_write = D_MDR_IN;
		end
		else begin
			d_write = D_ALU_IN;
		end

		if (C_RegWrite == 1)
		begin
			memory[a_write] <= d_write;
		end
		else begin
			a_write = 4'dx;
			d_write = 16'dx;
		end
end
	
always@(posedge clk or rst)
begin
	memory[4'b0000] = 16'b0000_0000_0000_0000;
	if (rst == 0) 
	begin
		D_ReadReg1RT <= memory[A_ReadReg1RT];
		D_ReadReg2RT <= memory[A_ReadReg2RT];
		D_Offset <= memory[A_Offset];
		D_RegSW <= memory[A_RegSWLW];
		D_BT <= memory[A_WriteRegRT_BT];
	end
	//else begin
		/*memory[4'd0] <= 16'd0;
		memory[4'd1] <= 16'd0;
		memory[4'd2] <= 16'd0;
		memory[4'd3] <= 16'd0;
		memory[4'd4] <= 16'd0;
		memory[4'd5] <= 16'd0;
		memory[4'd6] <= 16'd0;
		memory[4'd7] <= 16'd0;
		memory[4'd8] <= 16'd0;
		memory[4'd9] <= 16'd0;
		memory[4'd10] <= 16'd0;
		memory[4'd11] <= 16'd0;
		memory[4'd12] <= 16'd0;
		memory[4'd13] <= 16'd0;
		memory[4'd14] <= 16'd0;
		memory[4'd15] <= 16'd0;
	end */
	
end

endmodule

testbenches/tb_registerFile.v
module tb_registerFile();
	
	wire [15:0] D_ReadReg1RT, D_ReadReg2RT;
	wire [15:0] D_Offset, D_RegSW;
	wire [15:0] D_BT;

	reg [3:0] A_ReadReg1RT, A_ReadReg2RT;
	reg [3:0] A_Offset, A_RegSWLW;
	reg [3:0] A_WriteRegRT_BT;
	reg [15:0] D_MDR_IN, D_ALU_IN;

	reg C_RegDstWrite, C_RegWrite, C_MemToReg;
	reg clk, rst;

	registerFile uut(	D_ReadReg1RT, D_ReadReg2RT,
						D_Offset, D_RegSW,
						D_BT,
						D_MDR_IN, D_ALU_IN,	
						A_ReadReg1RT, A_ReadReg2RT,
						A_Offset, A_RegSWLW,
						A_WriteRegRT_BT,
						C_RegDstWrite, C_RegWrite, C_MemToReg,
						clk, rst
						);

	initial
	begin
		#00 clk = 1'b0;
		forever #10 clk = ~clk;
	end

	initial
	begin
		#5 rst = 1'b1;
		#27 rst = 1'b0; A_ReadReg1RT = 4'b0011; A_ReadReg2RT = 4'b0110; A_Offset = 4'b0010; A_RegSWLW = 4'b0111; A_WriteRegRT_BT = 4'b1110; 
		D_MDR_IN = 16'd154; D_ALU_IN = 16'd777;   	
		C_RegDstWrite = 1'b1; C_RegWrite = 1'b1; C_MemToReg = 1'b0;
		#55 rst = 1'b1;
		#27 rst = 1'b0; A_ReadReg1RT = 4'b0011; A_ReadReg2RT = 4'b0110; A_Offset = 4'b0010; A_RegSWLW = 4'b0111; A_WriteRegRT_BT = 4'b1110; 
		D_MDR_IN = 16'd154; D_ALU_IN = 16'd777;   	
		C_RegDstWrite = 1'b1; C_RegWrite = 1'b1; C_MemToReg = 1'b1;
		#55 rst = 1'b1;
		#27 rst = 1'b0; A_ReadReg1RT = 4'b0011; A_ReadReg2RT = 4'b0110; A_Offset = 4'b0010; A_RegSWLW = 4'b0111; A_WriteRegRT_BT = 4'b1110; 
		D_MDR_IN = 16'd154; D_ALU_IN = 16'd777;   	
		C_RegDstWrite = 1'b0; C_RegWrite = 1'b1; C_MemToReg = 1'b1;
		#55 rst = 1'b1;
		#27 rst = 1'b0; A_ReadReg1RT = 4'b0011; A_ReadReg2RT = 4'b0110; A_Offset = 4'b0010; A_RegSWLW = 4'b0111; A_WriteRegRT_BT = 4'b1110; 
		D_MDR_IN = 16'd154; D_ALU_IN = 16'd777;   	
		C_RegDstWrite = 1'b1; C_RegWrite = 1'b1; C_MemToReg = 1'b0;
		#55 rst = 1'b1;
		#27 rst = 1'b0; A_ReadReg1RT = 4'b0011; A_ReadReg2RT = 4'b0110; A_Offset = 4'b0010; A_RegSWLW = 4'b0111; A_WriteRegRT_BT = 4'b1110; 
		D_MDR_IN = 16'd154; D_ALU_IN = 16'd777;   	
		C_RegDstWrite = 1'b1; C_RegWrite = 1'b0; C_MemToReg = 1'b1;

		$stop;
	end

	initial
	begin
		$dumpfile("registerFile.vcd");
		$dumpvars;
	end
	
endmodule

concat11.v
module concat11(c11out, instr9to8);

	output wire [3:0] c11out;

	input wire [1:0] instr9to8;

	assign c11out = {2'b11, instr9to8};

endmodule

concat10.v
module concat10(c10out, instr10to11);
	
	output wire [3:0] c10out;
	
	input wire [1:0] instr10to11;
	
	assign c10out = {2'b10, instr10to11};

endmodule

assets/registerFile.vcd
$date
	Tue Apr 03 09:28:43 2018
$end
$version
	Icarus Verilog
$end
$timescale
	1s
$end
$scope module concat10 $end
$var wire 2 ! instr10to11 [1:0] $end
$var wire 4 " c10out [3:0] $end
$upscope $end
$scope module concat11 $end
$var wire 2 # instr9to8 [1:0] $end
$var wire 4 $ c11out [3:0] $end
$upscope $end
$scope module tb_registerFile $end
$var wire 16 % D_RegSW [15:0] $end
$var wire 16 & D_ReadReg2RT [15:0] $end
$var wire 16 ' D_ReadReg1RT [15:0] $end
$var wire 16 ( D_Offset [15:0] $end
$var wire 16 ) D_BT [15:0] $end
$var reg 4 * A_Offset [3:0] $end
$var reg 4 + A_ReadReg1RT [3:0] $end
$var reg 4 , A_ReadReg2RT [3:0] $end
$var reg 4 - A_RegSWLW [3:0] $end
$var reg 4 . A_WriteRegRT_BT [3:0] $end
$var reg 1 / C_MemToReg $end
$var reg 1 0 C_RegDstWrite $end
$var reg 1 1 C_RegWrite $end
$var reg 16 2 D_ALU_IN [15:0] $end
$var reg 16 3 D_MDR_IN [15:0] $end
$var reg 1 4 clk $end
$var reg 1 5 rst $end
$scope module uut $end
$var wire 4 6 A_Offset [3:0] $end
$var wire 4 7 A_ReadReg1RT [3:0] $end
$var wire 4 8 A_ReadReg2RT [3:0] $end
$var wire 4 9 A_RegSWLW [3:0] $end
$var wire 4 : A_WriteRegRT_BT [3:0] $end
$var wire 1 / C_MemToReg $end
$var wire 1 0 C_RegDstWrite $end
$var wire 1 1 C_RegWrite $end
$var wire 16 ; D_ALU_IN [15:0] $end
$var wire 16 < D_MDR_IN [15:0] $end
$var wire 1 4 clk $end
$var wire 1 5 rst $end
$var reg 16 = D_BT [15:0] $end
$var reg 16 > D_Offset [15:0] $end
$var reg 16 ? D_ReadReg1RT [15:0] $end
$var reg 16 @ D_ReadReg2RT [15:0] $end
$var reg 16 A D_RegSW [15:0] $end
$var reg 4 B a_write [3:0] $end
$var reg 16 C d_write [15:0] $end
$upscope $end
$upscope $end
$enddefinitions $end
#0
$dumpvars
bx C
bx B
bx A
bx @
bx ?
bx >
bx =
bx <
bx ;
bx :
bx 9
bx 8
bx 7
bx 6
x5
04
bx 3
bx 2
x1
x0
x/
bx .
bx -
bx ,
bx +
bx *
bx )
bx (
bx '
bx &
bx %
b11zz $
bz #
b10zz "
bz !
$end
#5
15
#10
14
#20
04
#30
14
#32
b0 )
b0 =
b0 %
b0 A
b0 (
b0 >
b0 &
b0 @
b0 '
b0 ?
b1100001001 C
b1110 B
0/
11
10
b1100001001 2
b1100001001 ;
b10011010 3
b10011010 <
b1110 .
b1110 :
b111 -
b111 9
b10 *
b10 6
b110 ,
b110 8
b11 +
b11 7
05
#40
04
#50
b1100001001 )
b1100001001 =
14
#60
04
#70
14
#80
04
#87
15
#90
14
#100
04
#110
14
#114
b0 )
b0 =
b10011010 C
1/
05
#120
04
#130
b10011010 )
b10011010 =
14
#140
04
#150
14
#160
04
#169
15
#170
14
#180
04
#190
14
#196
b0 )
b0 =
b111 B
00
05
#200
04
#210
b10011010 %
b10011010 A
14
#220
04
#230
14
#240
04
#250
14
#251
15
#260
04
#270
14
#278
b0 %
b0 A
b1100001001 C
b1110 B
0/
10
05
#280
04
#290
b1100001001 )
b1100001001 =
14
#300
04
#310
14
#320
04
#330
14
#333
15
